{
  "builds": [
    {
      "name": "amazon-ebs",
      "builder_type": "amazon-ebs",
      "build_time": 1583842940,
      "files": null,
      "artifact_id": "us-west-2:ami-06881ea36a626a466",
      "packer_run_uuid": "0d7466ce-5224-e1a1-18d4-a66b1f44648e"
    },
    {
      "name": "amazon-ebs",
      "builder_type": "amazon-ebs",
      "build_time": 1583850303,
      "files": null,
      "artifact_id": "us-west-2:ami-03e45e68d79eac18c",
      "packer_run_uuid": "2fae5914-2734-cecf-d835-33b8f6885704"
    }
  ],
  "last_run_uuid": "2fae5914-2734-cecf-d835-33b8f6885704"
}